Metadata-Version: 2.1
Name: easyCrawler
Version: 0.0.4
Summary: An easy crawler for new hands
Home-page: https://github.com/theCoder-WM
Author: William Ma
Author-email: 3327821469@qq.com
License: UNKNOWN
Platform: UNKNOWN
